{
    "id": 1594,
    "name": "   RANCID",
    "author": "fregoli",
    "creators": ["fregoli"],
    "verifier": "fregoli",
    "verification": "https://www.youtube.com/watch?v=ISTl28wKSXc",
    "percentToQualify": 78,
    "records": [
        {
            "user": "Gamer Boy",
            "link": "",
            "percent": 100,
            "hz": 407
        },
        {
            "user": "OzymandiasGD",
            "link": "",
            "percent": 100,
            "hz": 300
        }
    ]
}
